Metadata-Version: 2.1
Name: ghlinguist
Version: 1.1.0
Summary: simple command-line parser of GitHub Linguist Ruby program.
Home-page: https://github.com/scivision/linguist-python
Author: scivision
Author-email: scivision@users.noreply.github.com
Keywords: github,programming
Classifier: Development Status :: 5 - Production/Stable
Classifier: Environment :: Console
Classifier: Intended Audience :: Developers
Classifier: Intended Audience :: Information Technology
Classifier: Operating System :: OS Independent
Classifier: Programming Language :: Python :: 3
Classifier: Topic :: Software Development :: Libraries :: Ruby Modules
Classifier: Topic :: Text Processing :: Filters
Classifier: Topic :: Utilities
Requires-Python: >=3.7
Provides-Extra: tests
Provides-Extra: lint
License-File: LICENSE.txt
